wagtailclearstream/__init__.py
wagtailclearstream/stream.py
wagtailclearstream/wagtail_hooks.py
wagtailclearstream/static/.DS_Store
wagtailclearstream/static/wagtailclearstream/.DS_Store
wagtailclearstream/static/wagtailclearstream/css/wagtailclearstream.css
wagtailclearstream/static/wagtailclearstream/js/clear_stream.js
wagtailclearstream/templates/__init__.py
wagtailclearstream/templates/block_forms/__init__.py
wagtailclearstream-0.0.1.dist-info/DESCRIPTION.rst
wagtailclearstream-0.0.1.dist-info/METADATA
wagtailclearstream-0.0.1.dist-info/RECORD
wagtailclearstream-0.0.1.dist-info/WHEEL
wagtailclearstream-0.0.1.dist-info/metadata.json
wagtailclearstream-0.0.1.dist-info/top_level.txt
